dom_tokenizers/__init__.py
dom_tokenizers/train.py
dom_tokenizers/internal/__init__.py
dom_tokenizers/internal/json.py
dom_tokenizers/internal/jsonl.py
dom_tokenizers/internal/transformers.py
dom_tokenizers/pre_tokenizers/__init__.py
dom_tokenizers/pre_tokenizers/base64.py
dom_tokenizers/pre_tokenizers/compat_itertools.py
dom_tokenizers/pre_tokenizers/dom_snapshot.py
dom_tokenizers/pre_tokenizers/html.py
dom_tokenizers/pre_tokenizers/pre_tokenizer.py
dom_tokenizers/pre_tokenizers/splitter.py
dom_tokenizers/pre_tokenizers/token_buffer.py
dom_tokenizers/scripts/__init__.py
dom_tokenizers/scripts/defaults.py
dom_tokenizers/scripts/diff.py
dom_tokenizers/scripts/dump.py
dom_tokenizers/scripts/dump_breaking_inputs.py
dom_tokenizers/scripts/profile.py
dom_tokenizers-0.0.17.dist-info/LICENSE
dom_tokenizers-0.0.17.dist-info/METADATA
dom_tokenizers-0.0.17.dist-info/WHEEL
dom_tokenizers-0.0.17.dist-info/entry_points.txt
dom_tokenizers-0.0.17.dist-info/top_level.txt
dom_tokenizers-0.0.17.dist-info/RECORD
