Metadata-Version: 2.1
Name: dom-tokenizers
Version: 0.0.17
Summary: DOM-aware tokenization for 🤗 Hugging Face language models
Author-email: Gary Benson <gary@gbenson.net>
Project-URL: Homepage, https://github.com/gbenson/dom-tokenizers
Project-URL: Source, https://github.com/gbenson/dom-tokenizers
Classifier: Development Status :: 4 - Beta
Classifier: Intended Audience :: Developers
Classifier: Intended Audience :: Education
Classifier: Intended Audience :: Science/Research
Classifier: License :: OSI Approved :: Apache Software License
Classifier: Operating System :: OS Independent
Classifier: Programming Language :: Python :: 3
Classifier: Programming Language :: Python :: 3.10
Classifier: Programming Language :: Python :: 3.11
Classifier: Programming Language :: Python :: 3.12
Classifier: Topic :: Internet :: WWW/HTTP
Classifier: Topic :: Scientific/Engineering :: Artificial Intelligence
Classifier: Topic :: Scientific/Engineering :: Information Analysis
Classifier: Topic :: Text Processing :: Markup :: HTML
Requires-Python: >=3.10
License-File: LICENSE
Requires-Dist: python-magic
Requires-Dist: tokenizers
Requires-Dist: unidecode
Provides-Extra: dev
Requires-Dist: build ; extra == 'dev'
Requires-Dist: datasets ; extra == 'dev'
Requires-Dist: flake8 ; extra == 'dev'
Requires-Dist: flake8-custom-import-rules ; extra == 'dev'
Requires-Dist: flake8-quotes ; extra == 'dev'
Requires-Dist: pillow ; extra == 'dev'
Requires-Dist: pytest ; extra == 'dev'
Requires-Dist: pytest-cov ; extra == 'dev'
Requires-Dist: transformers ; extra == 'dev'
Provides-Extra: train
Requires-Dist: datasets ; extra == 'train'
Requires-Dist: pillow ; extra == 'train'
Requires-Dist: transformers ; extra == 'train'
